tdsbrondata/__init__.py
tdsbrondata/check.py
tdsbrondata/init.py
tdsbrondata/invoice.py
tdsbrondata/scd.py
tdsbrondata/source.py
tdsbrondata/utils.py
tdsbrondata-0.8.5.dist-info/METADATA
tdsbrondata-0.8.5.dist-info/WHEEL
tdsbrondata-0.8.5.dist-info/RECORD
