Metadata-Version: 2.4
Name: tdsbrondata
Version: 0.8.5
Summary: Tosch Data Solutions Brondata Library
Author-email: Tosch Data Solutions <data@tosch.nl>
Classifier: Development Status :: 3 - Alpha
Classifier: License :: OSI Approved :: Python Software Foundation License
Classifier: Natural Language :: English
Classifier: Operating System :: OS Independent
Classifier: Programming Language :: Python :: 3
Classifier: Topic :: Software Development :: Libraries :: Python Modules
Requires-Python: >=3.8
